dbt_datadict/__init__.py
dbt_datadict/__main__.py
dbt_datadict/apply.py
dbt_datadict/dbt_io.py
dbt_datadict/generate.py
dbt_datadict/utils.py
dbt_datadict-0.4.0.dist-info/licenses/LICENSE
dbt_datadict-0.4.0.dist-info/METADATA
dbt_datadict-0.4.0.dist-info/WHEEL
dbt_datadict-0.4.0.dist-info/entry_points.txt
dbt_datadict-0.4.0.dist-info/top_level.txt
dbt_datadict-0.4.0.dist-info/RECORD
