Metadata-Version: 2.4
Name: dbt-datadict
Version: 0.4.0
Summary: Tool for managing consistent column descriptions across a dbt project.
Author-email: tom <tom@tasman.ai>
License-Expression: GPL-3.0-only
Project-URL: homepage, https://github.com/TasmanAnalytics/dbt-datadictionary
Classifier: Development Status :: 3 - Alpha
Classifier: Programming Language :: Python :: 3.8
Classifier: Operating System :: OS Independent
Requires-Python: <4.0,>=3.10
License-File: LICENSE
Requires-Dist: ruamel.yaml<0.18,>=0.17.35
Requires-Dist: click>=8.3.0
Dynamic: license-file
